doodad/__init__.py
doodad/find_names.py
doodad/util.py
doodad-0.0.4.dist-info/LICENSE
doodad-0.0.4.dist-info/METADATA
doodad-0.0.4.dist-info/WHEEL
doodad-0.0.4.dist-info/top_level.txt
doodad-0.0.4.dist-info/RECORD
