Metadata-Version: 2.1
Name: doodad
Version: 0.0.4
Summary: Making access to names easier
Home-page: https://github.com/i2mint/doodad
Author: OtoSense
License: apache-2.0
Platform: any
License-File: LICENSE
